pyenergir/__init__.py
pyenergir/__main__.py
pyenergir/client.py
pyenergir/output.py
pyenergir-0.4.0.dist-info/LICENSE.txt
pyenergir-0.4.0.dist-info/METADATA
pyenergir-0.4.0.dist-info/WHEEL
pyenergir-0.4.0.dist-info/entry_points.txt
pyenergir-0.4.0.dist-info/top_level.txt
pyenergir-0.4.0.dist-info/RECORD
