Metadata-Version: 2.1
Name: pyenergir
Version: 0.4.0
Summary: Get your Energir consumption (wwww.energir.com)
Home-page: http://github.com/kevmegforest/pyenergir
Author: Kevin Forest
Author-email: kevmegforest@gmail.com
License: Apache 2.0
Platform: UNKNOWN
Classifier: Programming Language :: Python :: 3.4
Classifier: Programming Language :: Python :: 3.5
Classifier: Programming Language :: Python :: 3.6
Requires-Dist: aiohttp
Requires-Dist: bs4
Requires-Dist: python-dateutil
Requires-Dist: xlrd
